{
  "data": [{
    "工序": "凹二印",
    "班次": "白班",
    "机台": "W92C-10号",
    "机长": "刘洪",
    "品种": "9604A",
    "生产日期": "20190222",
    "生产记录": "1。开机前修补色模数开，停机配合电工安装流量计线路；2.下班清场未遗留过版纸在机台；"
  }, {
    "工序": "凹二印",
    "班次": "白班",
    "机台": "接线凹-2号",
    "机长": "张登军",
    "品种": "9607T",
    "生产日期": "20190222",
    "生产记录": "1.上班跑压印及辊子。2.中途电工点检，发现电箱有一组电源端子温度高，停机配合电工排查。（用时80分钟）3.已清场，无遗留过版纸。"
  }, {
    "工序": "凹一印",
    "班次": "白班",
    "机台": "W10-1号",
    "机长": "杨平",
    "品种": "9607T",
    "生产日期": "20190222",
    "生产记录": "1、班前清场；，2换压印3块，换辊子1根；3早上开机分纸头风管裂，找钳工换风管1根；4由于在线无法正常使用、故停机清洁在线光源，做白平衡，请中科在线工程人员全天调试在线；5、中途毡子跑故停机换毡子1次，清理色模1次；6、已清场无过版纸遗留机台"
  }],
  "rows": 3,
  "ip": "10.8.18.243",
  "header": ["工序", "班次", "机台", "机长", "品种", "生产日期", "生产记录"],
  "title": "质量平台_设备维修记录",
  "time": "1299.088ms",
  "source": "数据来源：MES_MAIN"
}